<?xml version="1.0" encoding="UTF-8"?>

<root xmlns:xsi="http://www.w3.org/2001/XMLSchema-instance"
	xsi:noNamespaceSchemaLocation="apinasajon.xsd">
	<models sistema="persona" modulo="Estagiario">
		<model>
			<nome>Novo</nome>
			<field nome="IdEstagiario" controlType="Guid" required="False" notnull="True"/>
			<field nome="Empresa" controlType="EntidadeFisicaJuridica" required="True" notnull="True"/>
			<field nome="Estabelecimento" controlType="EntidadeFisicaJuridica" required="True" notnull="True"/>
			<field nome="Departamento" controlType="EntidadeInterna" required="True" notnull="True"/>
			<field nome="Horario" controlType="EntidadeInterna" required="True" notnull="True"/>
			<field nome="Lotacao" controlType="EntidadeInterna" required="True" notnull="True"/>
			<field nome="NivelCargo" controlType="EntidadeInterna" required="True" notnull="True"/>
			<field nome="Cargo" controlType="EntidadeInterna" required="False" notnull="True"/>
			<field nome="Codigo" controlType="String" tamanho="14" required="True" notnull="True"/>
			<field nome="Nome" controlType="String" tamanho="80" required="True" notnull="True"/>			
			<field nome="CodigoCategoria" controlType="String" tamanho="3" required="True" notnull="True" summary="Conforme tabela de categorias do eSocial"/>		
			<field nome="CPF" controlType="String" tamanho="11" required="True" notnull="True" summary="[999.999.999-99]. A máscara não é obrigatória."/>
			<field nome="NIS" controlType="String" tamanho="11" required="True" notnull="True" summary="Informar o número do PIS, PASEP ou NIT"/>
			<field nome="DataInicioContrato" controlType="Date" required="True" notnull="True"/>			
			<field nome="DataFimContrato" controlType="Date" required="True" notnull="True"/>
			<field nome="UnidadeSalario" controlType="Integer" required="True" notnull="True" summary="Hora(1), Dia(2), Semana(3), Mês(4) ou Tarefa(5)"/>
			<field nome="Sexo" controlType="Integer" required="True" notnull="True" summary="Masculino(1) ou Feminino(2)"/>
			<field nome="CodigoCBO" controlType="String" tamanho="6" required="True" notnull="True" summary="Conforme tabela de código brasileiro de ocupações"/>
		</model>	
		<model>
			<nome>AlterarDadosGerais</nome>
			<field nome="Estagiario" controlType="EntidadeFisica" required="True" notnull="True"/>
			<field nome="Empresa" controlType="EntidadeFisicaJuridica" required="False" notnull="True"/>
			<field nome="Estabelecimento" controlType="EntidadeFisicaJuridica" required="False" notnull="True"/>
			<field nome="Departamento" controlType="EntidadeInterna" required="False" notnull="True"/>
			<field nome="Horario" controlType="EntidadeInterna" required="False" notnull="True"/>
			<field nome="Lotacao" controlType="EntidadeInterna" required="False" notnull="True"/>
			<field nome="NivelCargo" controlType="EntidadeInterna" required="False" notnull="True"/>
			<field nome="Cargo" controlType="EntidadeInterna" required="False" notnull="True"/>			
			<field nome="Codigo" controlType="String" tamanho="14" required="False" notnull="True"/>
			<field nome="Nome" controlType="String" tamanho="80" required="False" notnull="True"/>			
			<field nome="CodigoCategoria" controlType="String" tamanho="3" required="False" notnull="True" summary="Conforme tabela de categorias do eSocial"/>		
			<field nome="CPF" controlType="String" tamanho="11" required="False" notnull="True" summary="[999.999.999-99]. A máscara não é obrigatória."/>
			<field nome="NIS" controlType="String" tamanho="11" required="False" notnull="True" summary="Informar o número do PIS, PASEP ou NIT"/>
			<field nome="DataInicioContrato" controlType="Date" required="False" notnull="True"/>			
			<field nome="DataFimContrato" controlType="Date" required="False" notnull="True"/>			
			<field nome="UnidadeSalario" controlType="Integer" required="False" notnull="True" summary="Hora(1), Dia(2), Semana(3), Mês(4) ou Tarefa(5)"/>
			<field nome="Sexo" controlType="Integer" required="False" notnull="True" summary="Masculino(1) ou Feminino(2)"/>			
			<field nome="CodigoCBO" controlType="String" tamanho="6" required="False" notnull="True" summary="Conforme tabela de código brasileiro de ocupações"/>
		</model>	
		<model>
			<nome>AlterarDadosEndereco</nome>
			<field nome="Estagiario" controlType="EntidadeFisica" required="True" notnull="True"/>
			<field nome="Empresa" controlType="EntidadeFisicaJuridica" required="False" notnull="True"/>
			<field nome="TipoLogradouro" controlType="String" tamanho="10" required="False" notnull="False" summary="Conforme tabela de tipos de logradouro do eSocial"/>
			<field nome="CodigoMunicipio" controlType="String" tamanho="8" required="False" notnull="False" summary="Conforme tabela do IBGE"/>
			<field nome="CodigoPais" controlType="String" tamanho="5" required="False" notnull="False" summary="Conforme tabela oficial do governo"/>
			<field nome="Logradouro" controlType="String" tamanho="150" required="False" notnull="False"/>
			<field nome="Numero" controlType="String" tamanho="10" required="False" notnull="False"/>
			<field nome="Complemento" controlType="String" tamanho="60" required="False" notnull="False"/>
			<field nome="Bairro" controlType="String" tamanho="60" required="False" notnull="False"/>
			<field nome="Cidade" controlType="String" tamanho="60" required="False" notnull="False"/>
			<field nome="CEP" controlType="String" tamanho="10" required="False" notnull="False" summary="[99999-999]. A máscara não é obrigatória"/>
			<field nome="DDD" controlType="String" tamanho="2" required="False" notnull="False"/>			
			<field nome="Telefone" controlType="String" tamanho="20" required="False" notnull="False"/>			
		</model>	
		<model>
			<nome>AlterarDadosRecebimentoSalario</nome>
			<field nome="Estagiario" controlType="EntidadeFisica" required="True" notnull="True"/>
			<field nome="Empresa" controlType="EntidadeFisicaJuridica" required="False" notnull="True"/>
			<field nome="Tipo" controlType="Integer" required="False" notnull="False" summary="Conta Corrente(1), Conta Poupança(2), Conta Salário(4), Dinheiro(8) ou Cheque(16)"/>
			<field nome="NumeroConta" controlType="String" tamanho="14" required="False" notnull="False"/>
			<field nome="DigitoVerificador" controlType="String" tamanho="2" required="False" notnull="False"/>			
			<field nome="Agencia" controlType="EntidadeInterna" required="False" notnull="True"/>						
			<field nome="Banco" controlType="EntidadeInterna" required="False" notnull="True"/>						
		</model>	
		<model>
			<nome>AlterarDadosNascimento</nome>
			<field nome="Estagiario" controlType="EntidadeFisica" required="True" notnull="True"/>
			<field nome="Empresa" controlType="EntidadeFisicaJuridica" required="False" notnull="True"/>
			<field nome="UF" controlType="String" tamanho="2" required="False" notnull="False"/>
			<field nome="Cidade" controlType="String" tamanho="60" required="False" notnull="False"/>
			<field nome="CodigoMunicipio" controlType="String" tamanho="8" required="False" notnull="False" summary="Conforme tabela do IBGE"/>
			<field nome="CodigoPais" controlType="String" tamanho="5" required="False" notnull="False" summary="Conforme tabela oficial do governo"/>
			<field nome="NomePai" controlType="String" tamanho="80" required="False" notnull="False"/>
			<field nome="NomeMae" controlType="String" tamanho="80" required="False" notnull="False"/>
			<field nome="DataNascimento" controlType="Date" required="False" notnull="False"/>			
		</model>	
		<model>
			<nome>AlterarDadosCarteiraTrabalho</nome>
			<field nome="Estagiario" controlType="EntidadeFisica" required="True" notnull="True"/>
			<field nome="Empresa" controlType="EntidadeFisicaJuridica" required="False" notnull="True"/>
			<field nome="Numero" controlType="String" tamanho="11" required="False" notnull="False"/>
			<field nome="Serie" controlType="String" tamanho="5" required="False" notnull="False"/>
			<field nome="UF" controlType="String" tamanho="2" required="False" notnull="False"/>
			<field nome="DataExpedicao" controlType="Date" required="False" notnull="False"/>			
		</model>	
		<model>
			<nome>AlterarDadosEstagio</nome>
			<field nome="Estagiario" controlType="EntidadeFisica" required="True" notnull="True"/>
			<field nome="Empresa" controlType="EntidadeFisicaJuridica" required="False" notnull="True"/>
			<field nome="AreaAtuacao" controlType="String" tamanho="50" required="False" notnull="False"/>
			<field nome="ApoliceSeguro" controlType="String" tamanho="30" required="False" notnull="False"/>
			<field nome="NomeSupervisor" controlType="String" tamanho="60" required="False" notnull="False"/>
			<field nome="CPFSupervisor" controlType="String" tamanho="11" required="False" notnull="False"/>
			<field nome="Nivel" controlType="Integer" required="False" notnull="False" summary="Fundamental(1), Médio(2), Formação Profissional(3) ou Superior(4)"/>
			<field nome="Obrigatorio" controlType="Boolean" required="False" notnull="True"/>
			<field nome="InstituicaoEnsino" controlType="EntidadeInterna" required="False" notnull="False"/>
			<field nome="InstituicaoIntegradora" controlType="EntidadeInterna" required="False" notnull="False"/>			
		</model>
		<model>
			<nome>AlterarDadosNacionalidade</nome>
			<field nome="Estagiario" controlType="EntidadeFisica" required="True" notnull="True"/>
			<field nome="Empresa" controlType="EntidadeFisicaJuridica" required="False" notnull="True"/>
			<field nome="CodigoPais" controlType="String" tamanho="5" required="False" notnull="False" summary="Conforme tabela oficial do governo"/>
		</model>	
		<model>
			<nome>AlterarDadosRIC</nome>
			<field nome="Estagiario" controlType="EntidadeFisica" required="True" notnull="True"/>
			<field nome="Empresa" controlType="EntidadeFisicaJuridica" required="False" notnull="True"/>
			<field nome="Numero" controlType="String" tamanho="30" required="False" notnull="False"/>
			<field nome="OrgaoEmissor" controlType="String" tamanho="20" required="False" notnull="False"/>
			<field nome="UF" controlType="String" tamanho="2" required="False" notnull="False"/>
			<field nome="Cidade" controlType="String" tamanho="60" required="False" notnull="False"/>
			<field nome="DataExpedicao" controlType="Date" required="False" notnull="False"/>			
		</model>	
		<model>
			<nome>AlterarDadosCarteiraIdentidade</nome>
			<field nome="Estagiario" controlType="EntidadeFisica" required="True" notnull="True"/>
			<field nome="Empresa" controlType="EntidadeFisicaJuridica" required="False" notnull="True"/>
			<field nome="Numero" controlType="String" tamanho="30" required="False" notnull="False"/>
			<field nome="OrgaoEmissor" controlType="String" tamanho="20" required="False" notnull="False"/>
			<field nome="UF" controlType="String" tamanho="2" required="False" notnull="False"/>
			<field nome="DataExpedicao" controlType="Date" required="False" notnull="False"/>
		</model>	
		<model>
			<nome>AlterarDadosOrdemClasse</nome>
			<field nome="Estagiario" controlType="EntidadeFisica" required="True" notnull="True"/>
			<field nome="Empresa" controlType="EntidadeFisicaJuridica" required="False" notnull="True"/>
			<field nome="Numero" controlType="String" tamanho="14'" required="False" notnull="False"/>
			<field nome="OrgaoEmissor" controlType="String" tamanho="20" required="False" notnull="False"/>
			<field nome="DataExpedicao" controlType="Date" required="False" notnull="False"/>
			<field nome="DataValidade" controlType="Date" required="False" notnull="False"/>
		</model>	
		<model>
			<nome>AlterarDadosCarteiraHablilitacao</nome>
			<field nome="Estagiario" controlType="EntidadeFisica" required="True" notnull="True"/>
			<field nome="Empresa" controlType="EntidadeFisicaJuridica" required="False" notnull="True"/>
			<field nome="Numero" controlType="String" tamanho="30" required="False" notnull="False"/>
			<field nome="OrgaoEmissor" controlType="String" tamanho="20" required="False" notnull="False"/>
			<field nome="DataExpedicao" controlType="Date" required="False" notnull="False"/>
			<field nome="DataValidade" controlType="Date" required="False" notnull="False"/>			
			<field nome="DataPrimeiraHabilitacao" controlType="Date" required="False" notnull="False"/>
			<field nome="Categoria" controlType="Integer" required="False" notnull="False" summary="A(0), B(1), C(2), D(3), E(4), AB(5), AC(6), AD(7) ou AE(8)"/>
		</model>	
		<model>
			<nome>AlterarDadosValeTransporte</nome>
			<field nome="Estagiario" controlType="EntidadeFisica" required="True" notnull="True"/>
			<field nome="Empresa" controlType="EntidadeFisicaJuridica" required="False" notnull="True"/>
			<field nome="NumeroCartao" controlType="String" tamanho="16" required="False" notnull="False"/>
			<field nome="DiaSemanaComMeioVale" controlType="Integer" required="False" notnull="False" summary="De 1 a 7, começando pelo domingo"/>
		</model>	
		<model>
			<nome>AlterarDadosDeficiencia</nome>
			<field nome="Estagiario" controlType="EntidadeFisica" required="True" notnull="True"/>
			<field nome="Empresa" controlType="EntidadeFisicaJuridica" required="False" notnull="True"/>
			<field nome="DeficienteIntelectual" controlType="Boolean" required="False" notnull="False"/>
			<field nome="DeficienteMental" controlType="Boolean" required="False" notnull="False"/>
			<field nome="DeficienteAuditivo" controlType="Boolean" required="False" notnull="False"/>			
			<field nome="DeficienteVisual" controlType="Boolean" required="False" notnull="False"/>
			<field nome="DeficienteFisico" controlType="Boolean" required="False" notnull="False"/>
			<field nome="Reabilitado" controlType="Boolean" required="False" notnull="False"/>
		</model>	
		<model>
			<nome>AlterarDadosEstrangeiro</nome>
			<field nome="Estagiario" controlType="EntidadeFisica" required="True" notnull="True"/>
			<field nome="Empresa" controlType="EntidadeFisicaJuridica" required="False" notnull="True"/>
			<field nome="CasadoComBrasileiro" controlType="Boolean" required="False" notnull="False"/>
     		<field nome="TemFilhoBrasileiro" controlType="Boolean" required="False" notnull="False"/>
			<field nome="DataChegadaPais" controlType="Date" required="False" notnull="False"/>
			<field nome="DataNaturalizacao" controlType="Date" required="False" notnull="False"/>
			<field nome="NumeroNaturalizacao" controlType="String" tamanho="30" required="False" notnull="False"/>
		</model>
		<model>
			<nome>AlterarIdentidadeNasajon</nome>
			<field nome="Estagiario" controlType="EntidadeFisica" required="True" notnull="True"/>
			<field nome="Empresa" controlType="EntidadeFisicaJuridica" required="False" notnull="True"/>
			<field nome="Identidade" controlType="String" tamanho="250" required="True" notnull="False"/>
		</model>	
		<model>
			<nome>AlterarDadosJornada</nome>
			<field nome="Estagiario" controlType="EntidadeFisica" required="True" notnull="True"/>
			<field nome="Empresa" controlType="EntidadeFisicaJuridica" required="False" notnull="True"/>
			<field nome="QuantidadeMediaHorasSemanais" controlType="Integer" required="False" notnull="True"/>			
			<field nome="NumeroHorasMensais" controlType="Integer" required="False" notnull="True"/>
			<field nome="NumeroDiasPeriodo" controlType="Integer" required="False" notnull="True"/>		
		</model>	
		<model>
			<nome>AlterarSalario</nome>
			<field nome="Estagiario" controlType="EntidadeFisica" required="True" notnull="True"/>
			<field nome="Empresa" controlType="EntidadeFisicaJuridica" required="False" notnull="True"/>
			<field nome="SalarioFixo" controlType="Currency" tamanho="20,6"  required="False" notnull="True"/>
			<field nome="UnidadeSalario" controlType="Integer" required="False" notnull="True" summary="Hora(1), Dia(2), Semana(3), Mês(4) ou Tarefa(5)"/>
		</model>	
		<model>
			<nome>AlterarDadosPessoais</nome>
			<field nome="Estagiario" controlType="EntidadeFisica" required="True" notnull="True"/>
			<field nome="Empresa" controlType="EntidadeFisicaJuridica" required="False" notnull="True"/>
			<field nome="EstadoCivil" controlType="Integer" required="False" notnull="False" summary="Solteiro(1), Casado(2), Divorciado(3), Viúvo(4), União Estável(5) ou Outros(6)"/>
			<field nome="CodigoRaca" controlType="String" tamanho="1" required="False" notnull="True" summary="Conforme tabela oficial do governo"/>
			<field nome="CodigoGrauInstrucao" controlType="String" tamanho="2" required="False" notnull="True" summary="Conforme tabela oficial do governo"/>
		</model>	
		<model>
			<nome>AlterarDadosFerias</nome>
			<field nome="Estagiario" controlType="EntidadeFisica" required="True" notnull="True"/>
			<field nome="Empresa" controlType="EntidadeFisicaJuridica" required="False" notnull="True"/>
			<field nome="DataInicioPeriodoAquisitivo" controlType="Date" required="False" notnull="True"/>
			<field nome="DataProximasFerias" controlType="Date" required="False" notnull="False"/>
		</model>	
		<model>
			<nome>AlterarPercentualAdiantamento</nome>
			<field nome="Estagiario" controlType="EntidadeFisica" required="True" notnull="True"/>
			<field nome="Empresa" controlType="EntidadeFisicaJuridica" required="False" notnull="True"/>
			<field nome="Percentual" controlType="Currency" tamanho="20,6"  required="True" notnull="False"/>
		</model>	
		<model>
			<nome>AlterarAvalidador</nome>
			<field nome="Estagiario" controlType="EntidadeFisica" required="True" notnull="True"/>
			<field nome="Empresa" controlType="EntidadeFisicaJuridica" required="False" notnull="True"/>
			<field nome="Avaliador" controlType="EntidadeFisica" required="True" notnull="False"/>
		</model>	
		<model>
			<nome>AlterarGestor</nome>
			<field nome="Estagiario" controlType="EntidadeFisica" required="True" notnull="True"/>
			<field nome="Empresa" controlType="EntidadeFisicaJuridica" required="False" notnull="True"/>
			<field nome="Gestor" controlType="EntidadeFisica" required="True" notnull="False"/>
		</model>	
		<model>
			<nome>AlterarDataVencimentoAtestadoMedico</nome>
			<field nome="Estagiario" controlType="EntidadeFisica" required="True" notnull="True"/>
			<field nome="Empresa" controlType="EntidadeFisicaJuridica" required="False" notnull="True"/>
			<field nome="Data" controlType="Date" required="True" notnull="False"/>
		</model>	
		<model>
			<nome>AlterarObservacao</nome>
			<field nome="Estagiario" controlType="EntidadeFisica" required="True" notnull="True"/>
			<field nome="Empresa" controlType="EntidadeFisicaJuridica" required="False" notnull="True"/>
			<field nome="Observacao" controlType="Memo" required="True" notnull="True"/>			
		</model>
		<model>
			<nome>AlterarDadosAtividade</nome>
			<field nome="Estagiario" controlType="EntidadeFisica" required="True" notnull="True"/>
			<field nome="Empresa" controlType="EntidadeFisicaJuridica" required="False" notnull="True"/>
			<field nome="Atividade" controlType="Integer" required="True" notnull="True" summary="Rural(1) ou Urbana(2)"/>
		</model>
		<model>
			<nome>Excluir</nome>			
			<field nome="Estagiario" controlType="EntidadeFisica" required="True" notnull="True"/>
			<field nome="Empresa" controlType="EntidadeFisicaJuridica" required="False" notnull="True"/>
		</model>
	</models>
</root>